sspyjose/__init__.py
sspyjose/cryptography_aead_wrap.py
sspyjose/jwe.py
sspyjose/jwk.py
sspyjose/jws.py
sspyjose/nacl_aead_wrap.py
sspyjose/utils.py
sspyjose-0.2.6.dist-info/LICENSE.md
sspyjose-0.2.6.dist-info/METADATA
sspyjose-0.2.6.dist-info/WHEEL
sspyjose-0.2.6.dist-info/dependency_links.txt
sspyjose-0.2.6.dist-info/top_level.txt
sspyjose-0.2.6.dist-info/RECORD
