Metadata-Version: 2.1
Name: sspyjose
Version: 0.2.6
Summary: An (interim) JOSE library, featuring support for Ed25519, X25519, ChaCha20/Poly1305 and AES256-GCM as required for PyKauriID
Home-page: https://gitlab.com/kauriid/sspyjose.git
Author: Guy K. Kloss
Author-email: guy@mysinglesource.io
License: Apache License 2.0
Keywords: singlesource blockchain data kauri kauriid identity self-sovereign jose jwt jws jwe jwk
Platform: UNKNOWN
Classifier: Development Status :: 3 - Alpha
Classifier: Intended Audience :: Developers
Classifier: Topic :: Utilities
Classifier: License :: OSI Approved :: Apache Software License
Classifier: Programming Language :: Python :: 3
Classifier: Programming Language :: Python :: 3.6
Classifier: Programming Language :: Python :: 3.7
Requires-Dist: PyNaCl (>=1.3.0)
Requires-Dist: cryptography
Provides-Extra: dev
Requires-Dist: bumpversion ; extra == 'dev'
Requires-Dist: flake8 ; extra == 'dev'
Requires-Dist: flake8-docstrings ; extra == 'dev'
Requires-Dist: pep8-naming ; extra == 'dev'
Requires-Dist: flake8-bugbear ; extra == 'dev'
Requires-Dist: pypi-publisher ; extra == 'dev'
Requires-Dist: pre-commit ; extra == 'dev'
Provides-Extra: test
Requires-Dist: nose2 ; extra == 'test'
Requires-Dist: nose2-cov ; extra == 'test'
